schempy/__init__.py
schempy/components.py
schempy/constants.py
schempy/schematic.py
schempy/utils.py
schempy/schema/__init__.py
schempy/schema/v1.py
schempy/schema/v2.py
schempy/schema/v3.py
tests/__init__.py
tests/test_block.py
tests/test_palette.py
tests/test_schematic.py
tests/test_utils.py
SchemPy-0.0.12.dist-info/LICENSE
SchemPy-0.0.12.dist-info/METADATA
SchemPy-0.0.12.dist-info/WHEEL
SchemPy-0.0.12.dist-info/top_level.txt
SchemPy-0.0.12.dist-info/RECORD
